menusadp/__init__.py
menusadp/cli.py
menusadp/data/b.png
menusadp/data/default.html
menusadp/data/default.tex
menusadp/data/index.html
menusadp/data/logo_carre.png
menusadp/data/styling.css
menusadp/main.py
menusadp/upload.py
menusadp/utils.py
menusadp-6.0.1.dist-info/METADATA
menusadp-6.0.1.dist-info/WHEEL
menusadp-6.0.1.dist-info/entry_points.txt
menusadp-6.0.1.dist-info/RECORD
